README.rst
setup.cfg
setup.py
codewords/__init__.py
codewords/__main__.py
codewords/gen.py
codewords/version.py
codewords/words.py
codewords.egg-info/PKG-INFO
codewords.egg-info/SOURCES.txt
codewords.egg-info/dependency_links.txt
codewords.egg-info/entry_points.txt
codewords.egg-info/top_level.txt
tests/__init__.py
tests/simple.py