Metadata-Version: 1.1
Name: codewords
Version: 0.0.2
Summary: CodeWords python lbrary
Home-page: https://stash.movenetworks.com/projects/OPSTOOLS/
Author: Louis Zirkel III
Author-email: zzzirk@gmail.com
License: bsd3
Keywords: codewords
Platform: UNKNOWN
Classifier: Development Status :: 3 - Alpha
Classifier: Environment :: Console
Classifier: Intended Audience :: End Users/Desktop
Classifier: License :: OSI Approved :: BSD License
Classifier: Operating System :: OS Independent
Classifier: Programming Language :: Python
Classifier: Programming Language :: Python :: 2
Classifier: Programming Language :: Python :: 2.7
Classifier: Programming Language :: Python :: 3
Classifier: Programming Language :: Python :: 3.3
Classifier: Programming Language :: Python :: 3.4
Classifier: Programming Language :: Python :: 3.5
Classifier: Programming Language :: Python :: 3.6
Classifier: Topic :: Security
Classifier: Topic :: System
Classifier: Topic :: Utilities
